Metadata-Version: 2.4
Name: ChatterBot
Version: 1.2.12
Summary: ChatterBot is a machine learning, conversational dialog engine
Author: Gunther Cox
License-Expression: BSD-3-Clause
Project-URL: Documentation, https://docs.chatterbot.us
Project-URL: Repository, https://github.com/gunthercox/ChatterBot
Project-URL: Changelog, https://github.com/gunthercox/ChatterBot/releases
Keywords: ChatterBot,chatbot,chat,bot,natural language processing,nlp,artificial intelligence,ai
Classifier: Development Status :: 4 - Beta
Classifier: Intended Audience :: Developers
Classifier: Operating System :: OS Independent
Classifier: Environment :: Console
Classifier: Environment :: Web Environment
Classifier: Topic :: Internet
Classifier: Topic :: Software Development :: Libraries
Classifier: Topic :: Software Development :: Libraries :: Python Modules
Classifier: Topic :: Scientific/Engineering :: Artificial Intelligence
Classifier: Topic :: Scientific/Engineering :: Human Machine Interfaces
Classifier: Topic :: Communications :: Chat
Classifier: Topic :: Text Processing
Classifier: Topic :: Text Processing :: Filters
Classifier: Topic :: Text Processing :: General
Classifier: Topic :: Text Processing :: Indexing
Classifier: Topic :: Text Processing :: Linguistic
Classifier: Programming Language :: Python
Classifier: Programming Language :: Python :: 3
Classifier: Programming Language :: Python :: 3.9
Classifier: Programming Language :: Python :: 3 :: Only
Requires-Python: <3.14,>=3.9
License-File: LICENSE
Requires-Dist: mathparse<0.3,>=0.2
Requires-Dist: python-dateutil<2.10,>=2.9
Requires-Dist: sqlalchemy<2.1,>=2.0
Requires-Dist: spacy<3.9,>=3.8
Requires-Dist: tqdm
Provides-Extra: test
Requires-Dist: flake8; extra == "test"
Requires-Dist: coverage; extra == "test"
Requires-Dist: sphinx<9.2,>=5.3; extra == "test"
Requires-Dist: sphinx-sitemap>=2.6.0; extra == "test"
Requires-Dist: huggingface_hub; extra == "test"
Requires-Dist: django<6.0,<=4.1; extra == "test"
Provides-Extra: dev
Requires-Dist: pint>=0.8.1; extra == "dev"
Requires-Dist: pyyaml<7.0,>=6.0; extra == "dev"
Requires-Dist: chatterbot-corpus<1.3.0,>=1.2.2; extra == "dev"
Requires-Dist: ollama<1.0,>=0.6.0; extra == "dev"
Requires-Dist: openai; extra == "dev"
Provides-Extra: redis
Requires-Dist: redis[hiredis]<7.2,>=7.0; extra == "redis"
Requires-Dist: langchain-redis<0.3.0; extra == "redis"
Requires-Dist: langchain-huggingface<1.3.0,>=0.1.2; extra == "redis"
Requires-Dist: accelerate<1.13,>=1.6.0; extra == "redis"
Requires-Dist: sentence-transformers<5.3.0,>=4.0.2; extra == "redis"
Provides-Extra: mongodb
Requires-Dist: pymongo<4.17,>=4.11; extra == "mongodb"
Dynamic: license-file
